nuitka/Builtins.py
nuitka/BytecodeCaching.py
nuitka/Bytecodes.py
nuitka/CacheCleanup.py
nuitka/Constants.py
nuitka/Errors.py
nuitka/HardImportRegistry.py
nuitka/MainControl.py
nuitka/ModuleRegistry.py
nuitka/OptionParsing.py
nuitka/Options.py
nuitka/OutputDirectories.py
nuitka/PostProcessing.py
nuitka/Progress.py
nuitka/PythonFlavors.py
nuitka/PythonOperators.py
nuitka/PythonVersions.py
nuitka/Serialization.py
nuitka/SourceCodeReferences.py
nuitka/Tracing.py
nuitka/TreeXML.py
nuitka/Variables.py
nuitka/Version.py
nuitka/__init__.py
nuitka/__main__.py
nuitka/__past__.py
nuitka/build/Backend.scons
nuitka/build/CCompilerVersion.scons
nuitka/build/DataComposerInterface.py
nuitka/build/Offsets.scons
nuitka/build/Onefile.scons
nuitka/build/SconsCaching.py
nuitka/build/SconsCompilerSettings.py
nuitka/build/SconsHacks.py
nuitka/build/SconsInterface.py
nuitka/build/SconsProgress.py
nuitka/build/SconsPythonBuild.py
nuitka/build/SconsSpawn.py
nuitka/build/SconsUtils.py
nuitka/build/__init__.py
nuitka/build/include/nuitka/allocator.h
nuitka/build/include/nuitka/builtins.h
nuitka/build/include/nuitka/calling.h
nuitka/build/include/nuitka/checkers.h
nuitka/build/include/nuitka/checksum_tools.h
nuitka/build/include/nuitka/compiled_asyncgen.h
nuitka/build/include/nuitka/compiled_cell.h
nuitka/build/include/nuitka/compiled_coroutine.h
nuitka/build/include/nuitka/compiled_frame.h
nuitka/build/include/nuitka/compiled_function.h
nuitka/build/include/nuitka/compiled_generator.h
nuitka/build/include/nuitka/compiled_method.h
nuitka/build/include/nuitka/constants.h
nuitka/build/include/nuitka/constants_blob.h
nuitka/build/include/nuitka/debug_settings.h
nuitka/build/include/nuitka/environment_variables.h
nuitka/build/include/nuitka/environment_variables_system.h
nuitka/build/include/nuitka/exception_groups.h
nuitka/build/include/nuitka/exceptions.h
nuitka/build/include/nuitka/filesystem_paths.h
nuitka/build/include/nuitka/freelists.h
nuitka/build/include/nuitka/hedley.h
nuitka_winsvc-2.8.5.dist-info/licenses/LICENSE.txt
nuitka_winsvc-2.8.5.dist-info/METADATA
nuitka_winsvc-2.8.5.dist-info/WHEEL
nuitka_winsvc-2.8.5.dist-info/entry_points.txt
nuitka_winsvc-2.8.5.dist-info/top_level.txt
nuitka_winsvc-2.8.5.dist-info/RECORD
