Metadata-Version: 2.4
Name: Nuitka-winsvc
Version: 2.8.5
Summary: Nuitka but support compile as Windows service
Home-page: https://github.com/tabris17/Nuitka-winsvc
Author: tabris17
Author-email: tabris17.cn@gmail.com
License: Apache License, Version 2.0
Project-URL: Source, https://github.com/tabris17/Nuitka-winsvc
Keywords: windows service,compiler,python,nuitka
Classifier: Development Status :: 5 - Production/Stable
Classifier: Intended Audience :: Developers
Classifier: Intended Audience :: Science/Research
Classifier: Topic :: Software Development :: Compilers
Classifier: Topic :: Software Development :: Build Tools
Classifier: Topic :: Software Development :: Quality Assurance
Classifier: Topic :: System :: Software Distribution
Classifier: Programming Language :: Python :: 3.13
Classifier: Programming Language :: Python :: 3.12
Classifier: Programming Language :: Python :: 3.11
Classifier: Programming Language :: Python :: 3.10
Classifier: Programming Language :: Python :: 3.9
Classifier: Programming Language :: Python :: 3.8
Classifier: Programming Language :: Python :: 3.7
Classifier: Programming Language :: Python :: 3.6
Classifier: Programming Language :: Python :: 3.5
Classifier: Programming Language :: Python :: 3.4
Classifier: Programming Language :: Python :: 2.7
Classifier: Programming Language :: Python :: 2.6
Classifier: Programming Language :: Python :: Implementation :: CPython
Classifier: Programming Language :: C
Classifier: Operating System :: POSIX :: Linux
Classifier: Operating System :: POSIX :: BSD :: FreeBSD
Classifier: Operating System :: POSIX :: BSD :: NetBSD
Classifier: Operating System :: POSIX :: BSD :: OpenBSD
Classifier: Operating System :: Microsoft :: Windows
Classifier: Operating System :: MacOS
Classifier: Operating System :: Android
Classifier: License :: OSI Approved :: Apache Software License
License-File: LICENSE.txt
Requires-Dist: ordered-set>=4.1.0
Requires-Dist: zstandard>=0.15
Provides-Extra: build-wheel
Requires-Dist: setuptools>=42; extra == "build-wheel"
Requires-Dist: toml; extra == "build-wheel"
Requires-Dist: wheel; extra == "build-wheel"
Provides-Extra: package
Provides-Extra: standalone
Provides-Extra: onefile
Requires-Dist: zstandard>=0.15; extra == "onefile"
Provides-Extra: app
Requires-Dist: zstandard>=0.15; extra == "app"
Provides-Extra: icon-conversion
Requires-Dist: imageio; extra == "icon-conversion"
Provides-Extra: all
Requires-Dist: setuptools>=42; extra == "all"
Requires-Dist: toml; extra == "all"
Requires-Dist: zstandard>=0.15; extra == "all"
Requires-Dist: imageio; extra == "all"
Dynamic: author
Dynamic: author-email
Dynamic: classifier
Dynamic: description
Dynamic: description-content-type
Dynamic: home-page
Dynamic: keywords
Dynamic: license
Dynamic: license-file
Dynamic: project-url
Dynamic: provides-extra
Dynamic: requires-dist
Dynamic: summary
